LICENSE
README.md
setup.py
tempinbox/__init__.py
tempinbox.egg-info/PKG-INFO
tempinbox.egg-info/SOURCES.txt
tempinbox.egg-info/dependency_links.txt
tempinbox.egg-info/requires.txt
tempinbox.egg-info/top_level.txt