Metadata-Version: 2.1
Name: tempinbox
Version: 0.2.0
Summary: A Python package for generating temporary email addresses using Emailnator.
Home-page: https://github.com/ishanoshada/tempinbox
Author: Ishan Oshada
Author-email: ic31908@gamil.com
License: MIT
Platform: UNKNOWN
